{"recentFiles":[{"basename":"Figure Table","path":"Figure Table.md"},{"basename":"영국","path":"영국.md"},{"basename":"흄 David Hume","path":"흄 David Hume.md"},{"basename":"칸트 Immanuel Kant 1724~1804","path":"칸트 Immanuel Kant 1724~1804.md"},{"basename":"루소 Jean-Jacques Rousseau 1712~1778","path":"루소 Jean-Jacques Rousseau 1712~1778.md"},{"basename":"후설 Edmund Husserl 1859~1938","path":"후설 Edmund Husserl 1859~1938.md"},{"basename":"June 17th, 2021","path":"June 17th, 2021.md"}],"omittedPaths":[],"maxLength":null}